{
	"name": "SRC_DIMUB92RevenueCodes",
	"properties": {
		"linkedServiceName": {
			"referenceName": "AzureBlobStorage1",
			"type": "LinkedServiceReference"
		},
		"annotations": [],
		"type": "DelimitedText",
		"typeProperties": {
			"location": {
				"type": "AzureBlobStorageLocation",
				"fileName": "UB92 RevenueCodes.csv",
				"container": "p3kamlendu"
			},
			"columnDelimiter": ",",
			"escapeChar": "\\",
			"firstRowAsHeader": true,
			"quoteChar": "\""
		},
		"schema": [
			{
				"name": "Code",
				"type": "String"
			},
			{
				"name": "Description",
				"type": "String"
			}
		]
	}
}